[
    {
        "username": "mikey",
        "password": "1",
        "expiry": "2052-11-19",
        "hwid": [
            "e2d63abd68848fb996d45df7bd745983c01f52b054c10349a1e31a2191fe8761",
            "e619c095a6f9fdf5ab3f4ce33b031344c1371a2acea8d1a3fe056ca93e8fff5a",
            "d9f2d3bfaca095df25c5d9eb41ce961bab8bb7ea4e1d14c97cd02f9665a3b12f"
        ]
    },
    {
        "username": "x",
        "password": "x",
        "expiry": "2025-10-28",
        "hwid": []
    },
    {
        "username": "Golu",
        "password": "1",
        "expiry": "2028-07-24",
        "hwid": []
    },
    {
        "username": "1",
        "password": "1",
        "expiry": "2025-07-20",
        "hwid": []
    }
]